Metadata-Version: 2.1
Name: oxpy
Version: 1.5
Summary: Библиотека для взаимодействия с https://0x0.st через Python
Author: Neso Hiroshi
Author-email: neso_hoshi_official@mail.ru
Classifier: Programming Language :: Python :: 3
Classifier: License :: OSI Approved :: MIT License
Classifier: Operating System :: OS Independent
License-File: LICENSE
